ollamafreeapi/__init__.py
ollamafreeapi/client.py
ollamafreeapi/version.py
ollamafreeapi/ollama_json/deepseek.json
ollamafreeapi/ollama_json/gemma.json
ollamafreeapi/ollama_json/llama.json
ollamafreeapi/ollama_json/mistral.json
ollamafreeapi/ollama_json/others.json
ollamafreeapi/ollama_json/qwen.json
ollamafreeapi-0.1.2.dist-info/METADATA
ollamafreeapi-0.1.2.dist-info/WHEEL
ollamafreeapi-0.1.2.dist-info/top_level.txt
ollamafreeapi-0.1.2.dist-info/RECORD
