Metadata-Version: 2.4
Name: ollamafreeapi
Version: 0.1.2
Summary: A lightweight client for interacting with LLMs served via Ollama
Home-page: https://github.com/mfoud444/ollamafreeapi
Author: Mohammed Foud
Author-email: Mohammed Foud <mfoud444@gmail.com>
Project-URL: Homepage, https://github.com/mfoud444/ollamafreeapi
Project-URL: Bug Tracker, https://github.com/mfoud444/ollamafreeapi/issues
Classifier: Programming Language :: Python :: 3
Classifier: License :: OSI Approved :: MIT License
Classifier: Operating System :: OS Independent
Requires-Python: >=3.7
Requires-Dist: ollama>=0.1.0
Dynamic: author
Dynamic: home-page
Dynamic: requires-python
